django_tuieditor/__init__.py
django_tuieditor/apps.py
django_tuieditor/fields.py
django_tuieditor/models.py
django_tuieditor/widgets.py
django_tuieditor/static/django_tuieditor/codemirror.css
django_tuieditor/static/django_tuieditor/codemirror.js
django_tuieditor/static/django_tuieditor/django-fixes.css
django_tuieditor/static/django_tuieditor/django-fixes.js
django_tuieditor/static/django_tuieditor/toastui-editor-viewer.css
django_tuieditor/static/django_tuieditor/toastui-editor-viewer.js
django_tuieditor/static/django_tuieditor/toastui-editor.css
django_tuieditor/static/django_tuieditor/toastui-editor.js
django_tuieditor/templates/django_tuieditor/editor.html
django_tuieditor/templates/django_tuieditor/static_viewer.html
django_tuieditor/templates/django_tuieditor/viewer.html
django_tuieditor/templatetags/__init__.py
django_tuieditor/templatetags/gfm.py
django_tuieditor/templatetags/render_widget.py
django_tuieditor-0.2.0.dist-info/LICENSE
django_tuieditor-0.2.0.dist-info/LICENSE.TUI.Editor
django_tuieditor-0.2.0.dist-info/LICENSE.codemirror
django_tuieditor-0.2.0.dist-info/METADATA
django_tuieditor-0.2.0.dist-info/WHEEL
django_tuieditor-0.2.0.dist-info/top_level.txt
django_tuieditor-0.2.0.dist-info/RECORD
