Metadata-Version: 2.1
Name: django-tuieditor
Version: 0.2.0
Summary: Markdown editor and viewer widgets for Django
Home-page: https://github.com/QbDesu/django-tui.editor
Author: Qb
Author-email: qb@qbit.moe
License: UNKNOWN
Project-URL: Bug Tracker, https://github.com/QbDesu/django-tui.editor/issues
Platform: UNKNOWN
Classifier: Programming Language :: Python :: 3
Classifier: License :: OSI Approved :: MIT License
Classifier: Operating System :: OS Independent
Requires-Python: >=3.6
Requires-Dist: cmarkgfm
Requires-Dist: django
